COPYRIGHT
MANIFEST.in
Makefile
README
setup.py
test/__init__.py
test/__init__.pyc
test/test_compile.py
test/test_errors.py
test/__pycache__/test_compile.cpython-27-PYTEST.pyc
test/__pycache__/test_errors.cpython-27-PYTEST.pyc
tiddlywebplugins/__init__.py
tiddlywebplugins.prettyerror.egg-info/PKG-INFO
tiddlywebplugins.prettyerror.egg-info/SOURCES.txt
tiddlywebplugins.prettyerror.egg-info/dependency_links.txt
tiddlywebplugins.prettyerror.egg-info/namespace_packages.txt
tiddlywebplugins.prettyerror.egg-info/not-zip-safe
tiddlywebplugins.prettyerror.egg-info/requires.txt
tiddlywebplugins.prettyerror.egg-info/top_level.txt
tiddlywebplugins/prettyerror/__init__.py
tiddlywebplugins/prettyerror/config.py
tiddlywebplugins/prettyerror/exceptor.py
tiddlywebplugins/prettyerror/instance.py
tiddlywebplugins/prettyerror/resources/store/bags/_default_errors/description
tiddlywebplugins/prettyerror/resources/store/bags/_default_errors/policy
tiddlywebplugins/prettyerror/resources/store/bags/_default_errors/tiddlers/404/1
tiddlywebplugins/prettyerror/resources/store/bags/_default_errors/tiddlers/default/1