Metadata-Version: 1.0
Name: tiddlywebplugins.prettyerror
Version: 1.1.1
Summary: TiddlyWeb plugin for customizable HTTP error messages
Home-page: http://pypi.python.org/pypi/tiddlywebplugins.prettyerror
Author: Chris Dent
Author-email: cdent@peermore.com
License: BSD
Platform: Posix; MacOS X; Windows
